image2face/__init__.py
image2face/base_prediction.py
image2face/download_models.py
image2face/arcface/__init__.py
image2face/arcface/predict.py
image2face/arcface/backbones/__init__.py
image2face/arcface/backbones/iresnet.py
image2face/arcface/utils/__init__.py
image2face/arcface/utils/plot.py
image2face/arcface/utils/utils_amp.py
image2face/arcface/utils/utils_callbacks.py
image2face/arcface/utils/utils_logging.py
image2face/arcface/utils/utils_os.py
image2face/retinaface/__init__.py
image2face/retinaface/config.py
image2face/retinaface/predict.py
image2face/retinaface/train.py
image2face/retinaface/layers/__init__.py
image2face/retinaface/layers/functions/__init__.py
image2face/retinaface/layers/functions/prior_box.py
image2face/retinaface/layers/modules/__init__.py
image2face/retinaface/layers/modules/multibox_loss.py
image2face/retinaface/models/__init__.py
image2face/retinaface/models/net.py
image2face/retinaface/models/retinaface.py
image2face/retinaface/utils/__init__.py
image2face/retinaface/utils/box_utils.py
image2face/retinaface/utils/google_utils.py
image2face/retinaface/utils/timer.py
image2face/retinaface/utils/nms/__init__.py
image2face/retinaface/utils/nms/py_cpu_nms.py
image2face-0.2.1.dist-info/METADATA
image2face-0.2.1.dist-info/WHEEL
image2face-0.2.1.dist-info/top_level.txt
image2face-0.2.1.dist-info/RECORD
